{
  "defineConstant": {
    "DEBUG": true
  },
  "exclude": [
    "**/node_modules",
    "**/__pycache__",
    "**/tests"
  ],
  "executionEnvironments": [
    {
      "pythonVersion": "3.10",
      "root": "spider_toolsbox"
    }
  ],
  "include": [
    "spider_toolsbox"
  ],
  "pythonPlatform": "Linux",
  "pythonVersion": "3.10",
  "reportGeneralTypeIssues": false,
  "reportMissingImports": false,
  "reportMissingModuleSource": false,
  "reportMissingParameterType": false,
  "reportMissingTypeStubs": false,
  "reportUnknownArgumentType": false,
  "reportUnknownMemberType": false,
  "reportUnknownParameterType": false,
  "reportUnknownVariableType": false,
  "reportUntypedBaseClass": false,
  "reportUntypedFunctionDecorator": false,
  "reportUnusedFunction": "warning",
  "typeCheckingMode": "strict",
  "verboseOutput": true
}